limelight/__init__.py
limelight/api.py
limelight/errors.py
limelight/request.py
limelight/utils.py
limelight/validation_functions.py
limelight/membership/__init__.py
limelight/membership/errors.py
limelight/transaction/__init__.py
limelight/transaction/authorize_payment.py
limelight/transaction/new_order.py
limelight/transaction/new_order_card_on_file.py
limelight/transaction/new_order_with_prospect.py
limelight/transaction/new_prospect.py
limelight/transaction/three_d_redirect.py
python_limelight-1.1.dist-info/DESCRIPTION.rst
python_limelight-1.1.dist-info/METADATA
python_limelight-1.1.dist-info/metadata.json
python_limelight-1.1.dist-info/RECORD
python_limelight-1.1.dist-info/top_level.txt
python_limelight-1.1.dist-info/WHEEL
