Metadata-Version: 2.0
Name: python-limelight
Version: 1.1
Summary: A pythonic Lime Light API wrapper
Home-page: https://github.com/heropunch/python-limelight
Author: Carlos Killpack
Author-email: carlos.killpack@rocketmail.com
License: MIT
Platform: UNKNOWN
Classifier: Environment :: Web Environment
Classifier: Topic :: Internet
Classifier: Topic :: Office/Business
Classifier: Topic :: Office/Business :: Financial
Classifier: Topic :: Office/Business :: Financial :: Accounting
Classifier: Topic :: Office/Business :: Financial :: Investment
Classifier: Topic :: Office/Business :: Financial :: Point-Of-Sale
Classifier: License :: OSI Approved
Classifier: License :: OSI Approved :: MIT License
Classifier: Programming Language :: Python :: 2
Classifier: Programming Language :: Python :: 3
Classifier: Programming Language :: Python :: Implementation :: PyPy
Requires-Dist: validate-email-address (>=1)
Requires-Dist: requests
Requires-Dist: ipaddress
Requires-Dist: voluptuous
Requires-Dist: pycountry
Requires-Dist: six
